pyg_encoders/__init__.py
pyg_encoders/_dump.py
pyg_encoders/_encode.py
pyg_encoders/_encoders.py
pyg_encoders/_locks.py
pyg_encoders/_parquet.py
pyg_encoders/_threads.py
pyg_encoders/_writers.py
pyg_encoders-0.0.30.dist-info/licenses/LICENSE.txt
pyg_encoders-0.0.30.dist-info/METADATA
pyg_encoders-0.0.30.dist-info/WHEEL
pyg_encoders-0.0.30.dist-info/top_level.txt
pyg_encoders-0.0.30.dist-info/RECORD
