Metadata-Version: 2.4
Name: pyg-encoders
Version: 0.0.30
Summary: Utilities for encoding DataFrame/Series within a document as npy parquet or csv files
Home-page: https://github.com/gityoav/pyg-encoders
Author: Yoav Git
Author-email: yoav.git@gmail.com
Project-URL: Bug Tracker, https://github.com/gityoav/pyg-encoders/issues
Classifier: Programming Language :: Python :: 3
Classifier: License :: OSI Approved :: GNU General Public License v3 (GPLv3)
Classifier: Operating System :: OS Independent
Requires-Python: >=3.6
License-File: LICENSE.txt
Requires-Dist: pyg-base
Requires-Dist: pyg-npy
Dynamic: license-file
